sockjsChat/__init__.py
sockjsChat/multiplex.py
sockjsChat/server.py
sockjsChat/settings.py
sockjsChat/urls.py
sockjsChat/utils.py
sockjsChat/apps/__init__.py
sockjsChat/apps/main/__init__.py
sockjsChat/apps/main/urls.py
sockjsChat/apps/main/views.py
sockjsChat/static/css/style.css
sockjsChat/static/js/date.js
sockjsChat/static/js/multiplex.js
sockjsChat/static/js/script.js
sockjsChat/templates/chat.html
sockjsChat/templates/index.html
sockjsChat/templates/multiplex.html
sockjsChat-1.1.0.dist-info/DESCRIPTION.rst
sockjsChat-1.1.0.dist-info/METADATA
sockjsChat-1.1.0.dist-info/RECORD
sockjsChat-1.1.0.dist-info/WHEEL
sockjsChat-1.1.0.dist-info/entry_points.txt
sockjsChat-1.1.0.dist-info/metadata.json
sockjsChat-1.1.0.dist-info/top_level.txt
