Metadata-Version: 2.0
Name: sockjsChat
Version: 1.1.0
Summary: A Chat Server based on sockjs, websocket and tornado
Home-page: https://github.com/anirbanroydas/sockjsChat
Author: Anirban Roy Das
Author-email: anirban.nick@gmail.com
License: MIT
Keywords: chat server sockjs websocket tornado
Platform: UNKNOWN
Classifier: Development Status :: 4 - Beta
Classifier: Intended Audience :: Developers
Classifier: License :: OSI Approved :: MIT License
Classifier: Natural Language :: English
Classifier: Operating System :: OS Independent
Classifier: Programming Language :: Python
Classifier: Programming Language :: Python :: 2
Classifier: Programming Language :: Python :: 2.7
Classifier: Programming Language :: Python :: Implementation :: CPython
Requires-Dist: setuptools (>=0.7.0)
Requires-Dist: sockjs-tornado
Requires-Dist: tornado (>=2.2.1)
